headless_coder_sdk/gemini_cli/__init__.py
headless_coder_sdk/gemini_cli/adapter.py
headless_coder_sdk_gemini_cli-0.1.0.dist-info/METADATA
headless_coder_sdk_gemini_cli-0.1.0.dist-info/WHEEL
headless_coder_sdk_gemini_cli-0.1.0.dist-info/licenses/LICENSE
headless_coder_sdk_gemini_cli-0.1.0.dist-info/RECORD
