Metadata-Version: 2.4
Name: headless-coder-sdk-gemini-cli
Version: 0.1.0
Summary: Gemini CLI adapter for the Python headless coder SDK.
Project-URL: Homepage, https://github.com/OhadAssulin/headless-coder-sdk
Project-URL: Source, https://github.com/OhadAssulin/python-headless-coder
Author: Ohad Assulin
License: MIT License
License-File: LICENSE
Keywords: ai,cli,gemini,sdk
Classifier: Intended Audience :: Developers
Classifier: License :: OSI Approved :: MIT License
Classifier: Programming Language :: Python :: 3
Classifier: Programming Language :: Python :: 3.9
Requires-Python: >=3.9
Requires-Dist: headless-coder-sdk-core>=0.1.0
Requires-Dist: typing-extensions>=4.9
